{
  "formatVersion": 1,
  "database": {
    "version": 4,
    "identityHash": "a93f3107b46183eaa5ff246e577c5b4b",
    "entities": [
      {
        "tableName": "servers",
        "createSql": "CREATE TABLE IF NOT EXISTS `${TABLE_NAME}` (`id` INTEGER PRIMARY KEY AUTOINCREMENT NOT NULL, `name` TEXT NOT NULL, `kind` TEXT NOT NULL, `baseUrl` TEXT NOT NULL, `username` TEXT NOT NULL, `password` TEXT NOT NULL, `playlistUrl` TEXT NOT NULL, `createdAt` INTEGER NOT NULL, `lastSyncAt` INTEGER NOT NULL, `host` TEXT NOT NULL, `accountStatus` TEXT NOT NULL, `expiryDate` INTEGER NOT NULL, `activeConnections` INTEGER NOT NULL, `maxConnections` INTEGER NOT NULL, `allowedOutputFormats` TEXT NOT NULL, `timezone` TEXT NOT NULL, `serverMessage` TEXT NOT NULL, `lastSyncSource` TEXT NOT NULL)",
        "fields": [
          {
            "fieldPath": "id",
            "columnName": "id",
            "affinity": "INTEGER",
            "notNull": true
          },
          {
            "fieldPath": "name",
            "columnName": "name",
            "affinity": "TEXT",
            "notNull": true
          },
          {
            "fieldPath": "kind",
            "columnName": "kind",
            "affinity": "TEXT",
            "notNull": true
          },
          {
            "fieldPath": "baseUrl",
            "columnName": "baseUrl",
            "affinity": "TEXT",
            "notNull": true
          },
          {
            "fieldPath": "username",
            "columnName": "username",
            "affinity": "TEXT",
            "notNull": true
          },
          {
            "fieldPath": "password",
            "columnName": "password",
            "affinity": "TEXT",
            "notNull": true
          },
          {
            "fieldPath": "playlistUrl",
            "columnName": "playlistUrl",
            "affinity": "TEXT",
            "notNull": true
          },
          {
            "fieldPath": "createdAt",
            "columnName": "createdAt",
            "affinity": "INTEGER",
            "notNull": true
          },
          {
            "fieldPath": "lastSyncAt",
            "columnName": "lastSyncAt",
            "affinity": "INTEGER",
            "notNull": true
          },
          {
            "fieldPath": "host",
            "columnName": "host",
            "affinity": "TEXT",
            "notNull": true
          },
          {
            "fieldPath": "accountStatus",
            "columnName": "accountStatus",
            "affinity": "TEXT",
            "notNull": true
          },
          {
            "fieldPath": "expiryDate",
            "columnName": "expiryDate",
            "affinity": "INTEGER",
            "notNull": true
          },
          {
            "fieldPath": "activeConnections",
            "columnName": "activeConnections",
            "affinity": "INTEGER",
            "notNull": true
          },
          {
            "fieldPath": "maxConnections",
            "columnName": "maxConnections",
            "affinity": "INTEGER",
            "notNull": true
          },
          {
            "fieldPath": "allowedOutputFormats",
            "columnName": "allowedOutputFormats",
            "affinity": "TEXT",
            "notNull": true
          },
          {
            "fieldPath": "timezone",
            "columnName": "timezone",
            "affinity": "TEXT",
            "notNull": true
          },
          {
            "fieldPath": "serverMessage",
            "columnName": "serverMessage",
            "affinity": "TEXT",
            "notNull": true
          },
          {
            "fieldPath": "lastSyncSource",
            "columnName": "lastSyncSource",
            "affinity": "TEXT",
            "notNull": true
          }
        ],
        "primaryKey": {
          "autoGenerate": true,
          "columnNames": [
            "id"
          ]
        }
      },
      {
        "tableName": "categories",
        "createSql": "CREATE TABLE IF NOT EXISTS `${TABLE_NAME}` (`id` TEXT NOT NULL, `serverId` INTEGER NOT NULL, `type` TEXT NOT NULL, `name` TEXT NOT NULL, `sortOrder` INTEGER NOT NULL, `parentId` TEXT NOT NULL, `rawJson` TEXT NOT NULL, PRIMARY KEY(`id`, `serverId`, `type`))",
        "fields": [
          {
            "fieldPath": "id",
            "columnName": "id",
            "affinity": "TEXT",
            "notNull": true
          },
          {
            "fieldPath": "serverId",
            "columnName": "serverId",
            "affinity": "INTEGER",
            "notNull": true
          },
          {
            "fieldPath": "type",
            "columnName": "type",
            "affinity": "TEXT",
            "notNull": true
          },
          {
            "fieldPath": "name",
            "columnName": "name",
            "affinity": "TEXT",
            "notNull": true
          },
          {
            "fieldPath": "sortOrder",
            "columnName": "sortOrder",
            "affinity": "INTEGER",
            "notNull": true
          },
          {
            "fieldPath": "parentId",
            "columnName": "parentId",
            "affinity": "TEXT",
            "notNull": true
          },
          {
            "fieldPath": "rawJson",
            "columnName": "rawJson",
            "affinity": "TEXT",
            "notNull": true
          }
        ],
        "primaryKey": {
          "autoGenerate": false,
          "columnNames": [
            "id",
            "serverId",
            "type"
          ]
        },
        "indices": [
          {
            "name": "index_categories_serverId_type",
            "unique": false,
            "columnNames": [
              "serverId",
              "type"
            ],
            "orders": [],
            "createSql": "CREATE INDEX IF NOT EXISTS `index_categories_serverId_type` ON `${TABLE_NAME}` (`serverId`, `type`)"
          },
          {
            "name": "index_categories_serverId_type_sortOrder",
            "unique": false,
            "columnNames": [
              "serverId",
              "type",
              "sortOrder"
            ],
            "orders": [],
            "createSql": "CREATE INDEX IF NOT EXISTS `index_categories_serverId_type_sortOrder` ON `${TABLE_NAME}` (`serverId`, `type`, `sortOrder`)"
          }
        ]
      },
      {
        "tableName": "media",
        "createSql": "CREATE TABLE IF NOT EXISTS `${TABLE_NAME}` (`id` TEXT NOT NULL, `serverId` INTEGER NOT NULL, `type` TEXT NOT NULL, `categoryId` TEXT NOT NULL, `categoryName` TEXT NOT NULL, `title` TEXT NOT NULL, `streamUrl` TEXT NOT NULL, `posterUrl` TEXT NOT NULL, `backdropUrl` TEXT NOT NULL, `description` TEXT NOT NULL, `rating` TEXT NOT NULL, `durationSecs` INTEGER NOT NULL, `addedAt` INTEGER NOT NULL, `lastModifiedAt` INTEGER NOT NULL, `addedAtUnknown` INTEGER NOT NULL, `serverOrder` INTEGER NOT NULL, `containerExtension` TEXT NOT NULL, `seriesId` TEXT NOT NULL, `seasonNumber` INTEGER NOT NULL, `episodeNumber` INTEGER NOT NULL, `isFavorite` INTEGER NOT NULL, `watchPositionMs` INTEGER NOT NULL, `watchDurationMs` INTEGER NOT NULL, `tvgId` TEXT NOT NULL, `catchup` TEXT NOT NULL, `cast` TEXT NOT NULL, `director` TEXT NOT NULL, `genre` TEXT NOT NULL, `releaseDate` TEXT NOT NULL, `rawJson` TEXT NOT NULL, `updatedAt` INTEGER NOT NULL, PRIMARY KEY(`id`, `serverId`, `type`))",
        "fields": [
          {
            "fieldPath": "id",
            "columnName": "id",
            "affinity": "TEXT",
            "notNull": true
          },
          {
            "fieldPath": "serverId",
            "columnName": "serverId",
            "affinity": "INTEGER",
            "notNull": true
          },
          {
            "fieldPath": "type",
            "columnName": "type",
            "affinity": "TEXT",
            "notNull": true
          },
          {
            "fieldPath": "categoryId",
            "columnName": "categoryId",
            "affinity": "TEXT",
            "notNull": true
          },
          {
            "fieldPath": "categoryName",
            "columnName": "categoryName",
            "affinity": "TEXT",
            "notNull": true
          },
          {
            "fieldPath": "title",
            "columnName": "title",
            "affinity": "TEXT",
            "notNull": true
          },
          {
            "fieldPath": "streamUrl",
            "columnName": "streamUrl",
            "affinity": "TEXT",
            "notNull": true
          },
          {
            "fieldPath": "posterUrl",
            "columnName": "posterUrl",
            "affinity": "TEXT",
            "notNull": true
          },
          {
            "fieldPath": "backdropUrl",
            "columnName": "backdropUrl",
            "affinity": "TEXT",
            "notNull": true
          },
          {
            "fieldPath": "description",
            "columnName": "description",
            "affinity": "TEXT",
            "notNull": true
          },
          {
            "fieldPath": "rating",
            "columnName": "rating",
            "affinity": "TEXT",
            "notNull": true
          },
          {
            "fieldPath": "durationSecs",
            "columnName": "durationSecs",
            "affinity": "INTEGER",
            "notNull": true
          },
          {
            "fieldPath": "addedAt",
            "columnName": "addedAt",
            "affinity": "INTEGER",
            "notNull": true
          },
          {
            "fieldPath": "lastModifiedAt",
            "columnName": "lastModifiedAt",
            "affinity": "INTEGER",
            "notNull": true
          },
          {
            "fieldPath": "addedAtUnknown",
            "columnName": "addedAtUnknown",
            "affinity": "INTEGER",
            "notNull": true
          },
          {
            "fieldPath": "serverOrder",
            "columnName": "serverOrder",
            "affinity": "INTEGER",
            "notNull": true
          },
          {
            "fieldPath": "containerExtension",
            "columnName": "containerExtension",
            "affinity": "TEXT",
            "notNull": true
          },
          {
            "fieldPath": "seriesId",
            "columnName": "seriesId",
            "affinity": "TEXT",
            "notNull": true
          },
          {
            "fieldPath": "seasonNumber",
            "columnName": "seasonNumber",
            "affinity": "INTEGER",
            "notNull": true
          },
          {
            "fieldPath": "episodeNumber",
            "columnName": "episodeNumber",
            "affinity": "INTEGER",
            "notNull": true
          },
          {
            "fieldPath": "isFavorite",
            "columnName": "isFavorite",
            "affinity": "INTEGER",
            "notNull": true
          },
          {
            "fieldPath": "watchPositionMs",
            "columnName": "watchPositionMs",
            "affinity": "INTEGER",
            "notNull": true
          },
          {
            "fieldPath": "watchDurationMs",
            "columnName": "watchDurationMs",
            "affinity": "INTEGER",
            "notNull": true
          },
          {
            "fieldPath": "tvgId",
            "columnName": "tvgId",
            "affinity": "TEXT",
            "notNull": true
          },
          {
            "fieldPath": "catchup",
            "columnName": "catchup",
            "affinity": "TEXT",
            "notNull": true
          },
          {
            "fieldPath": "cast",
            "columnName": "cast",
            "affinity": "TEXT",
            "notNull": true
          },
          {
            "fieldPath": "director",
            "columnName": "director",
            "affinity": "TEXT",
            "notNull": true
          },
          {
            "fieldPath": "genre",
            "columnName": "genre",
            "affinity": "TEXT",
            "notNull": true
          },
          {
            "fieldPath": "releaseDate",
            "columnName": "releaseDate",
            "affinity": "TEXT",
            "notNull": true
          },
          {
            "fieldPath": "rawJson",
            "columnName": "rawJson",
            "affinity": "TEXT",
            "notNull": true
          },
          {
            "fieldPath": "updatedAt",
            "columnName": "updatedAt",
            "affinity": "INTEGER",
            "notNull": true
          }
        ],
        "primaryKey": {
          "autoGenerate": false,
          "columnNames": [
            "id",
            "serverId",
            "type"
          ]
        },
        "indices": [
          {
            "name": "index_media_serverId",
            "unique": false,
            "columnNames": [
              "serverId"
            ],
            "orders": [],
            "createSql": "CREATE INDEX IF NOT EXISTS `index_media_serverId` ON `${TABLE_NAME}` (`serverId`)"
          },
          {
            "name": "index_media_type",
            "unique": false,
            "columnNames": [
              "type"
            ],
            "orders": [],
            "createSql": "CREATE INDEX IF NOT EXISTS `index_media_type` ON `${TABLE_NAME}` (`type`)"
          },
          {
            "name": "index_media_categoryId",
            "unique": false,
            "columnNames": [
              "categoryId"
            ],
            "orders": [],
            "createSql": "CREATE INDEX IF NOT EXISTS `index_media_categoryId` ON `${TABLE_NAME}` (`categoryId`)"
          },
          {
            "name": "index_media_categoryName",
            "unique": false,
            "columnNames": [
              "categoryName"
            ],
            "orders": [],
            "createSql": "CREATE INDEX IF NOT EXISTS `index_media_categoryName` ON `${TABLE_NAME}` (`categoryName`)"
          },
          {
            "name": "index_media_title",
            "unique": false,
            "columnNames": [
              "title"
            ],
            "orders": [],
            "createSql": "CREATE INDEX IF NOT EXISTS `index_media_title` ON `${TABLE_NAME}` (`title`)"
          },
          {
            "name": "index_media_addedAt",
            "unique": false,
            "columnNames": [
              "addedAt"
            ],
            "orders": [],
            "createSql": "CREATE INDEX IF NOT EXISTS `index_media_addedAt` ON `${TABLE_NAME}` (`addedAt`)"
          },
          {
            "name": "index_media_lastModifiedAt",
            "unique": false,
            "columnNames": [
              "lastModifiedAt"
            ],
            "orders": [],
            "createSql": "CREATE INDEX IF NOT EXISTS `index_media_lastModifiedAt` ON `${TABLE_NAME}` (`lastModifiedAt`)"
          },
          {
            "name": "index_media_serverOrder",
            "unique": false,
            "columnNames": [
              "serverOrder"
            ],
            "orders": [],
            "createSql": "CREATE INDEX IF NOT EXISTS `index_media_serverOrder` ON `${TABLE_NAME}` (`serverOrder`)"
          },
          {
            "name": "index_media_seriesId",
            "unique": false,
            "columnNames": [
              "seriesId"
            ],
            "orders": [],
            "createSql": "CREATE INDEX IF NOT EXISTS `index_media_seriesId` ON `${TABLE_NAME}` (`seriesId`)"
          },
          {
            "name": "index_media_serverId_type_categoryId",
            "unique": false,
            "columnNames": [
              "serverId",
              "type",
              "categoryId"
            ],
            "orders": [],
            "createSql": "CREATE INDEX IF NOT EXISTS `index_media_serverId_type_categoryId` ON `${TABLE_NAME}` (`serverId`, `type`, `categoryId`)"
          },
          {
            "name": "index_media_serverId_type_title",
            "unique": false,
            "columnNames": [
              "serverId",
              "type",
              "title"
            ],
            "orders": [],
            "createSql": "CREATE INDEX IF NOT EXISTS `index_media_serverId_type_title` ON `${TABLE_NAME}` (`serverId`, `type`, `title`)"
          },
          {
            "name": "index_media_serverId_type_serverOrder",
            "unique": false,
            "columnNames": [
              "serverId",
              "type",
              "serverOrder"
            ],
            "orders": [],
            "createSql": "CREATE INDEX IF NOT EXISTS `index_media_serverId_type_serverOrder` ON `${TABLE_NAME}` (`serverId`, `type`, `serverOrder`)"
          },
          {
            "name": "index_media_serverId_type_addedAt",
            "unique": false,
            "columnNames": [
              "serverId",
              "type",
              "addedAt"
            ],
            "orders": [],
            "createSql": "CREATE INDEX IF NOT EXISTS `index_media_serverId_type_addedAt` ON `${TABLE_NAME}` (`serverId`, `type`, `addedAt`)"
          },
          {
            "name": "index_media_serverId_seriesId_type",
            "unique": false,
            "columnNames": [
              "serverId",
              "seriesId",
              "type"
            ],
            "orders": [],
            "createSql": "CREATE INDEX IF NOT EXISTS `index_media_serverId_seriesId_type` ON `${TABLE_NAME}` (`serverId`, `seriesId`, `type`)"
          },
          {
            "name": "index_media_serverId_isFavorite_updatedAt",
            "unique": false,
            "columnNames": [
              "serverId",
              "isFavorite",
              "updatedAt"
            ],
            "orders": [],
            "createSql": "CREATE INDEX IF NOT EXISTS `index_media_serverId_isFavorite_updatedAt` ON `${TABLE_NAME}` (`serverId`, `isFavorite`, `updatedAt`)"
          },
          {
            "name": "index_media_serverId_watchPositionMs_updatedAt",
            "unique": false,
            "columnNames": [
              "serverId",
              "watchPositionMs",
              "updatedAt"
            ],
            "orders": [],
            "createSql": "CREATE INDEX IF NOT EXISTS `index_media_serverId_watchPositionMs_updatedAt` ON `${TABLE_NAME}` (`serverId`, `watchPositionMs`, `updatedAt`)"
          }
        ]
      },
      {
        "tableName": "account_info",
        "createSql": "CREATE TABLE IF NOT EXISTS `${TABLE_NAME}` (`serverId` INTEGER NOT NULL, `status` TEXT NOT NULL, `expiryDate` INTEGER NOT NULL, `activeConnections` INTEGER NOT NULL, `maxConnections` INTEGER NOT NULL, `allowedOutputFormats` TEXT NOT NULL, `createdAt` INTEGER NOT NULL, `isTrial` INTEGER NOT NULL, `usernameMasked` TEXT NOT NULL, `rawJson` TEXT NOT NULL, `updatedAt` INTEGER NOT NULL, PRIMARY KEY(`serverId`))",
        "fields": [
          {
            "fieldPath": "serverId",
            "columnName": "serverId",
            "affinity": "INTEGER",
            "notNull": true
          },
          {
            "fieldPath": "status",
            "columnName": "status",
            "affinity": "TEXT",
            "notNull": true
          },
          {
            "fieldPath": "expiryDate",
            "columnName": "expiryDate",
            "affinity": "INTEGER",
            "notNull": true
          },
          {
            "fieldPath": "activeConnections",
            "columnName": "activeConnections",
            "affinity": "INTEGER",
            "notNull": true
          },
          {
            "fieldPath": "maxConnections",
            "columnName": "maxConnections",
            "affinity": "INTEGER",
            "notNull": true
          },
          {
            "fieldPath": "allowedOutputFormats",
            "columnName": "allowedOutputFormats",
            "affinity": "TEXT",
            "notNull": true
          },
          {
            "fieldPath": "createdAt",
            "columnName": "createdAt",
            "affinity": "INTEGER",
            "notNull": true
          },
          {
            "fieldPath": "isTrial",
            "columnName": "isTrial",
            "affinity": "INTEGER",
            "notNull": true
          },
          {
            "fieldPath": "usernameMasked",
            "columnName": "usernameMasked",
            "affinity": "TEXT",
            "notNull": true
          },
          {
            "fieldPath": "rawJson",
            "columnName": "rawJson",
            "affinity": "TEXT",
            "notNull": true
          },
          {
            "fieldPath": "updatedAt",
            "columnName": "updatedAt",
            "affinity": "INTEGER",
            "notNull": true
          }
        ],
        "primaryKey": {
          "autoGenerate": false,
          "columnNames": [
            "serverId"
          ]
        },
        "indices": [
          {
            "name": "index_account_info_updatedAt",
            "unique": false,
            "columnNames": [
              "updatedAt"
            ],
            "orders": [],
            "createSql": "CREATE INDEX IF NOT EXISTS `index_account_info_updatedAt` ON `${TABLE_NAME}` (`updatedAt`)"
          }
        ]
      },
      {
        "tableName": "server_info",
        "createSql": "CREATE TABLE IF NOT EXISTS `${TABLE_NAME}` (`serverId` INTEGER NOT NULL, `url` TEXT NOT NULL, `timezone` TEXT NOT NULL, `timestampNow` INTEGER NOT NULL, `timeNow` TEXT NOT NULL, `message` TEXT NOT NULL, `rawJson` TEXT NOT NULL, `updatedAt` INTEGER NOT NULL, PRIMARY KEY(`serverId`))",
        "fields": [
          {
            "fieldPath": "serverId",
            "columnName": "serverId",
            "affinity": "INTEGER",
            "notNull": true
          },
          {
            "fieldPath": "url",
            "columnName": "url",
            "affinity": "TEXT",
            "notNull": true
          },
          {
            "fieldPath": "timezone",
            "columnName": "timezone",
            "affinity": "TEXT",
            "notNull": true
          },
          {
            "fieldPath": "timestampNow",
            "columnName": "timestampNow",
            "affinity": "INTEGER",
            "notNull": true
          },
          {
            "fieldPath": "timeNow",
            "columnName": "timeNow",
            "affinity": "TEXT",
            "notNull": true
          },
          {
            "fieldPath": "message",
            "columnName": "message",
            "affinity": "TEXT",
            "notNull": true
          },
          {
            "fieldPath": "rawJson",
            "columnName": "rawJson",
            "affinity": "TEXT",
            "notNull": true
          },
          {
            "fieldPath": "updatedAt",
            "columnName": "updatedAt",
            "affinity": "INTEGER",
            "notNull": true
          }
        ],
        "primaryKey": {
          "autoGenerate": false,
          "columnNames": [
            "serverId"
          ]
        }
      },
      {
        "tableName": "vod_details",
        "createSql": "CREATE TABLE IF NOT EXISTS `${TABLE_NAME}` (`serverId` INTEGER NOT NULL, `vodId` TEXT NOT NULL, `movieImage` TEXT NOT NULL, `backdrop` TEXT NOT NULL, `plot` TEXT NOT NULL, `cast` TEXT NOT NULL, `director` TEXT NOT NULL, `genre` TEXT NOT NULL, `releaseDate` TEXT NOT NULL, `rating` TEXT NOT NULL, `duration` TEXT NOT NULL, `country` TEXT NOT NULL, `youtubeTrailer` TEXT NOT NULL, `rawJson` TEXT NOT NULL, `updatedAt` INTEGER NOT NULL, PRIMARY KEY(`serverId`, `vodId`))",
        "fields": [
          {
            "fieldPath": "serverId",
            "columnName": "serverId",
            "affinity": "INTEGER",
            "notNull": true
          },
          {
            "fieldPath": "vodId",
            "columnName": "vodId",
            "affinity": "TEXT",
            "notNull": true
          },
          {
            "fieldPath": "movieImage",
            "columnName": "movieImage",
            "affinity": "TEXT",
            "notNull": true
          },
          {
            "fieldPath": "backdrop",
            "columnName": "backdrop",
            "affinity": "TEXT",
            "notNull": true
          },
          {
            "fieldPath": "plot",
            "columnName": "plot",
            "affinity": "TEXT",
            "notNull": true
          },
          {
            "fieldPath": "cast",
            "columnName": "cast",
            "affinity": "TEXT",
            "notNull": true
          },
          {
            "fieldPath": "director",
            "columnName": "director",
            "affinity": "TEXT",
            "notNull": true
          },
          {
            "fieldPath": "genre",
            "columnName": "genre",
            "affinity": "TEXT",
            "notNull": true
          },
          {
            "fieldPath": "releaseDate",
            "columnName": "releaseDate",
            "affinity": "TEXT",
            "notNull": true
          },
          {
            "fieldPath": "rating",
            "columnName": "rating",
            "affinity": "TEXT",
            "notNull": true
          },
          {
            "fieldPath": "duration",
            "columnName": "duration",
            "affinity": "TEXT",
            "notNull": true
          },
          {
            "fieldPath": "country",
            "columnName": "country",
            "affinity": "TEXT",
            "notNull": true
          },
          {
            "fieldPath": "youtubeTrailer",
            "columnName": "youtubeTrailer",
            "affinity": "TEXT",
            "notNull": true
          },
          {
            "fieldPath": "rawJson",
            "columnName": "rawJson",
            "affinity": "TEXT",
            "notNull": true
          },
          {
            "fieldPath": "updatedAt",
            "columnName": "updatedAt",
            "affinity": "INTEGER",
            "notNull": true
          }
        ],
        "primaryKey": {
          "autoGenerate": false,
          "columnNames": [
            "serverId",
            "vodId"
          ]
        },
        "indices": [
          {
            "name": "index_vod_details_updatedAt",
            "unique": false,
            "columnNames": [
              "updatedAt"
            ],
            "orders": [],
            "createSql": "CREATE INDEX IF NOT EXISTS `index_vod_details_updatedAt` ON `${TABLE_NAME}` (`updatedAt`)"
          }
        ]
      },
      {
        "tableName": "seasons",
        "createSql": "CREATE TABLE IF NOT EXISTS `${TABLE_NAME}` (`serverId` INTEGER NOT NULL, `seriesId` TEXT NOT NULL, `seasonNumber` INTEGER NOT NULL, `name` TEXT NOT NULL, `cover` TEXT NOT NULL, `airDate` TEXT NOT NULL, `plot` TEXT NOT NULL, `rawJson` TEXT NOT NULL, `updatedAt` INTEGER NOT NULL, PRIMARY KEY(`serverId`, `seriesId`, `seasonNumber`))",
        "fields": [
          {
            "fieldPath": "serverId",
            "columnName": "serverId",
            "affinity": "INTEGER",
            "notNull": true
          },
          {
            "fieldPath": "seriesId",
            "columnName": "seriesId",
            "affinity": "TEXT",
            "notNull": true
          },
          {
            "fieldPath": "seasonNumber",
            "columnName": "seasonNumber",
            "affinity": "INTEGER",
            "notNull": true
          },
          {
            "fieldPath": "name",
            "columnName": "name",
            "affinity": "TEXT",
            "notNull": true
          },
          {
            "fieldPath": "cover",
            "columnName": "cover",
            "affinity": "TEXT",
            "notNull": true
          },
          {
            "fieldPath": "airDate",
            "columnName": "airDate",
            "affinity": "TEXT",
            "notNull": true
          },
          {
            "fieldPath": "plot",
            "columnName": "plot",
            "affinity": "TEXT",
            "notNull": true
          },
          {
            "fieldPath": "rawJson",
            "columnName": "rawJson",
            "affinity": "TEXT",
            "notNull": true
          },
          {
            "fieldPath": "updatedAt",
            "columnName": "updatedAt",
            "affinity": "INTEGER",
            "notNull": true
          }
        ],
        "primaryKey": {
          "autoGenerate": false,
          "columnNames": [
            "serverId",
            "seriesId",
            "seasonNumber"
          ]
        },
        "indices": [
          {
            "name": "index_seasons_seriesId",
            "unique": false,
            "columnNames": [
              "seriesId"
            ],
            "orders": [],
            "createSql": "CREATE INDEX IF NOT EXISTS `index_seasons_seriesId` ON `${TABLE_NAME}` (`seriesId`)"
          }
        ]
      },
      {
        "tableName": "epg_programs",
        "createSql": "CREATE TABLE IF NOT EXISTS `${TABLE_NAME}` (`serverId` INTEGER NOT NULL, `channelKey` TEXT NOT NULL, `title` TEXT NOT NULL, `description` TEXT NOT NULL, `startAt` INTEGER NOT NULL, `endAt` INTEGER NOT NULL, `category` TEXT NOT NULL, `rawJson` TEXT NOT NULL, `updatedAt` INTEGER NOT NULL, PRIMARY KEY(`serverId`, `channelKey`, `startAt`, `title`))",
        "fields": [
          {
            "fieldPath": "serverId",
            "columnName": "serverId",
            "affinity": "INTEGER",
            "notNull": true
          },
          {
            "fieldPath": "channelKey",
            "columnName": "channelKey",
            "affinity": "TEXT",
            "notNull": true
          },
          {
            "fieldPath": "title",
            "columnName": "title",
            "affinity": "TEXT",
            "notNull": true
          },
          {
            "fieldPath": "description",
            "columnName": "description",
            "affinity": "TEXT",
            "notNull": true
          },
          {
            "fieldPath": "startAt",
            "columnName": "startAt",
            "affinity": "INTEGER",
            "notNull": true
          },
          {
            "fieldPath": "endAt",
            "columnName": "endAt",
            "affinity": "INTEGER",
            "notNull": true
          },
          {
            "fieldPath": "category",
            "columnName": "category",
            "affinity": "TEXT",
            "notNull": true
          },
          {
            "fieldPath": "rawJson",
            "columnName": "rawJson",
            "affinity": "TEXT",
            "notNull": true
          },
          {
            "fieldPath": "updatedAt",
            "columnName": "updatedAt",
            "affinity": "INTEGER",
            "notNull": true
          }
        ],
        "primaryKey": {
          "autoGenerate": false,
          "columnNames": [
            "serverId",
            "channelKey",
            "startAt",
            "title"
          ]
        },
        "indices": [
          {
            "name": "index_epg_programs_serverId_channelKey_startAt",
            "unique": false,
            "columnNames": [
              "serverId",
              "channelKey",
              "startAt"
            ],
            "orders": [],
            "createSql": "CREATE INDEX IF NOT EXISTS `index_epg_programs_serverId_channelKey_startAt` ON `${TABLE_NAME}` (`serverId`, `channelKey`, `startAt`)"
          },
          {
            "name": "index_epg_programs_serverId_startAt",
            "unique": false,
            "columnNames": [
              "serverId",
              "startAt"
            ],
            "orders": [],
            "createSql": "CREATE INDEX IF NOT EXISTS `index_epg_programs_serverId_startAt` ON `${TABLE_NAME}` (`serverId`, `startAt`)"
          }
        ]
      },
      {
        "tableName": "sync_state",
        "createSql": "CREATE TABLE IF NOT EXISTS `${TABLE_NAME}` (`serverId` INTEGER NOT NULL, `source` TEXT NOT NULL, `status` TEXT NOT NULL, `lastSyncAt` INTEGER NOT NULL, `liveSyncedAt` INTEGER NOT NULL, `vodSyncedAt` INTEGER NOT NULL, `seriesSyncedAt` INTEGER NOT NULL, `epgSyncedAt` INTEGER NOT NULL, `lastError` TEXT NOT NULL, `rawJson` TEXT NOT NULL, `updatedAt` INTEGER NOT NULL, PRIMARY KEY(`serverId`))",
        "fields": [
          {
            "fieldPath": "serverId",
            "columnName": "serverId",
            "affinity": "INTEGER",
            "notNull": true
          },
          {
            "fieldPath": "source",
            "columnName": "source",
            "affinity": "TEXT",
            "notNull": true
          },
          {
            "fieldPath": "status",
            "columnName": "status",
            "affinity": "TEXT",
            "notNull": true
          },
          {
            "fieldPath": "lastSyncAt",
            "columnName": "lastSyncAt",
            "affinity": "INTEGER",
            "notNull": true
          },
          {
            "fieldPath": "liveSyncedAt",
            "columnName": "liveSyncedAt",
            "affinity": "INTEGER",
            "notNull": true
          },
          {
            "fieldPath": "vodSyncedAt",
            "columnName": "vodSyncedAt",
            "affinity": "INTEGER",
            "notNull": true
          },
          {
            "fieldPath": "seriesSyncedAt",
            "columnName": "seriesSyncedAt",
            "affinity": "INTEGER",
            "notNull": true
          },
          {
            "fieldPath": "epgSyncedAt",
            "columnName": "epgSyncedAt",
            "affinity": "INTEGER",
            "notNull": true
          },
          {
            "fieldPath": "lastError",
            "columnName": "lastError",
            "affinity": "TEXT",
            "notNull": true
          },
          {
            "fieldPath": "rawJson",
            "columnName": "rawJson",
            "affinity": "TEXT",
            "notNull": true
          },
          {
            "fieldPath": "updatedAt",
            "columnName": "updatedAt",
            "affinity": "INTEGER",
            "notNull": true
          }
        ],
        "primaryKey": {
          "autoGenerate": false,
          "columnNames": [
            "serverId"
          ]
        }
      }
    ],
    "setupQueries": [
      "CREATE TABLE IF NOT EXISTS room_master_table (id INTEGER PRIMARY KEY,identity_hash TEXT)",
      "INSERT OR REPLACE INTO room_master_table (id,identity_hash) VALUES(42, 'a93f3107b46183eaa5ff246e577c5b4b')"
    ]
  }
}